odoo/addons/stock_location_orderpoint_source_relocate/README.rst
odoo/addons/stock_location_orderpoint_source_relocate/__init__.py
odoo/addons/stock_location_orderpoint_source_relocate/__manifest__.py
odoo/addons/stock_location_orderpoint_source_relocate/i18n/it.po
odoo/addons/stock_location_orderpoint_source_relocate/i18n/stock_location_orderpoint_source_relocate.pot
odoo/addons/stock_location_orderpoint_source_relocate/models/__init__.py
odoo/addons/stock_location_orderpoint_source_relocate/models/stock_location_orderpoint.py
odoo/addons/stock_location_orderpoint_source_relocate/models/stock_move.py
odoo/addons/stock_location_orderpoint_source_relocate/readme/CONTRIBUTORS.rst
odoo/addons/stock_location_orderpoint_source_relocate/readme/DESCRIPTION.rst
odoo/addons/stock_location_orderpoint_source_relocate/static/description/icon.png
odoo/addons/stock_location_orderpoint_source_relocate/static/description/index.html
odoo/addons/stock_location_orderpoint_source_relocate/tests/__init__.py
odoo/addons/stock_location_orderpoint_source_relocate/tests/test_location_orderpoint.py
odoo14_addon_stock_location_orderpoint_source_relocate-14.0.1.0.3.dist-info/METADATA
odoo14_addon_stock_location_orderpoint_source_relocate-14.0.1.0.3.dist-info/WHEEL
odoo14_addon_stock_location_orderpoint_source_relocate-14.0.1.0.3.dist-info/top_level.txt
odoo14_addon_stock_location_orderpoint_source_relocate-14.0.1.0.3.dist-info/RECORD
