Metadata-Version: 2.1
Name: odoo14-addon-stock-location-orderpoint-source-relocate
Version: 14.0.1.0.3
Summary: Run an auto location orderpoint replenishment after the move relocation done by Stock Move Source Relocate
Home-page: https://github.com/OCA/stock-logistics-warehouse
Author: MT Software, BCIM, Odoo Community Association (OCA)
Author-email: support@odoo-community.org
License: AGPL-3
Platform: UNKNOWN
Classifier: Programming Language :: Python
Classifier: Framework :: Odoo
Classifier: Framework :: Odoo :: 14.0
Classifier: License :: OSI Approved :: GNU Affero General Public License v3
Classifier: Development Status :: 3 - Alpha
Requires-Python: >=3.6
Requires-Dist: odoo14-addon-stock-location-orderpoint
Requires-Dist: odoo14-addon-stock-move-source-relocate
Requires-Dist: odoo <14.1dev,>=14.0a
